{"total": 68.5, "children": [{"total": 10.0, "size": 1, "children": [{"size": 1.0, "name": "2.4", "name-long": "Food production/agriculture"}, {"size": 1.0, "name": "6.5", "name-long": "Water resources management"}, {"size": 1.0, "name": "6.6", "name-long": "Water-related ecosystems"}, {"size": 2.0, "name": "12.1", "name-long": "Sustainable consumption/production"}, {"size": 1.0, "name": "12.5", "name-long": "Waste"}, {"size": 1.0, "name": "13.1", "name-long": "Climate change adaptation"}, {"size": 1.0, "name": "14.4", "name-long": "Fishery"}, {"size": 1.0, "name": "14.1", "name-long": "Marine pollution"}, {"size": 1.0, "name": "15.2", "name-long": "Forests"}], "name": "2.2", "name-long": "Malnutrition"}, {"total": 26.0, "size": 2, "children": [{"size": 2.0, "name": "2.2", "name-long": "Malnutrition"}, {"size": 3.0, "name": "6.5", "name-long": "Water resources management"}, {"size": 3.0, "name": "6.6", "name-long": "Water-related ecosystems"}, {"size": 2.5, "name": "12.1", "name-long": "Sustainable consumption/production"}, {"size": 2.5, "name": "12.5", "name-long": "Waste"}, {"size": 3.0, "name": "13.1", "name-long": "Climate change adaptation"}, {"size": 3.5, "name": "14.4", "name-long": "Fishery"}, {"size": 3.0, "name": "14.1", "name-long": "Marine pollution"}, {"size": 3.5, "name": "15.2", "name-long": "Forests"}], "name": "2.4", "name-long": "Food production/agriculture"}, {"total": 16.5, "size": 1, "children": [{"size": 1.0, "name": "2.2", "name-long": "Malnutrition"}, {"size": 2.0, "name": "2.4", "name-long": "Food production/agriculture"}, {"size": 2.5, "name": "6.6", "name-long": "Water-related ecosystems"}, {"size": 1.5, "name": "12.1", "name-long": "Sustainable consumption/production"}, {"size": 1.5, "name": "12.5", "name-long": "Waste"}, {"size": 2.0, "name": "13.1", "name-long": "Climate change adaptation"}, {"size": 2.0, "name": "14.4", "name-long": "Fishery"}, {"size": 2.5, "name": "14.1", "name-long": "Marine pollution"}, {"size": 1.5, "name": "15.2", "name-long": "Forests"}], "name": "6.5", "name-long": "Water resources management"}, {"total": 21.5, "size": 2, "children": [{"size": 2.0, "name": "2.2", "name-long": "Malnutrition"}, {"size": 2.5, "name": "2.4", "name-long": "Food production/agriculture"}, {"size": 3.0, "name": "6.5", "name-long": "Water resources management"}, {"size": 2.0, "name": "12.1", "name-long": "Sustainable consumption/production"}, {"size": 2.0, "name": "12.5", "name-long": "Waste"}, {"size": 3.0, "name": "13.1", "name-long": "Climate change adaptation"}, {"size": 2.0, "name": "14.4", "name-long": "Fishery"}, {"size": 2.0, "name": "14.1", "name-long": "Marine pollution"}, {"size": 3.0, "name": "15.2", "name-long": "Forests"}], "name": "6.6", "name-long": "Water-related ecosystems"}, {"total": 17.0, "size": 1, "children": [{"size": 1.5, "name": "2.2", "name-long": "Malnutrition"}, {"size": 2.0, "name": "2.4", "name-long": "Food production/agriculture"}, {"size": 2.0, "name": "6.5", "name-long": "Water resources management"}, {"size": 1.5, "name": "6.6", "name-long": "Water-related ecosystems"}, {"size": 2.0, "name": "12.5", "name-long": "Waste"}, {"size": 2.0, "name": "13.1", "name-long": "Climate change adaptation"}, {"size": 1.5, "name": "14.4", "name-long": "Fishery"}, {"size": 2.5, "name": "14.1", "name-long": "Marine pollution"}, {"size": 2.0, "name": "15.2", "name-long": "Forests"}], "name": "12.1", "name-long": "Sustainable consumption/production"}, {"total": 14.0, "size": 1, "children": [{"size": 1.0, "name": "2.2", "name-long": "Malnutrition"}, {"size": 1.5, "name": "2.4", "name-long": "Food production/agriculture"}, {"size": 1.5, "name": "6.5", "name-long": "Water resources management"}, {"size": 1.5, "name": "6.6", "name-long": "Water-related ecosystems"}, {"size": 2.5, "name": "12.1", "name-long": "Sustainable consumption/production"}, {"size": 1.5, "name": "13.1", "name-long": "Climate change adaptation"}, {"size": 1.0, "name": "14.4", "name-long": "Fishery"}, {"size": 2.0, "name": "14.1", "name-long": "Marine pollution"}, {"size": 1.5, "name": "15.2", "name-long": "Forests"}], "name": "12.5", "name-long": "Waste"}, {"total": 14.0, "size": 1, "children": [{"size": 1.5, "name": "2.2", "name-long": "Malnutrition"}, {"size": 2.5, "name": "2.4", "name-long": "Food production/agriculture"}, {"size": 2.0, "name": "6.5", "name-long": "Water resources management"}, {"size": 2.5, "name": "6.6", "name-long": "Water-related ecosystems"}, {"size": 1.0, "name": "12.1", "name-long": "Sustainable consumption/production"}, {"size": 1.0, "name": "12.5", "name-long": "Waste"}, {"size": 1.0, "name": "14.4", "name-long": "Fishery"}, {"size": 1.0, "name": "14.1", "name-long": "Marine pollution"}, {"size": 1.5, "name": "15.2", "name-long": "Forests"}], "name": "13.1", "name-long": "Climate change adaptation"}, {"total": 31.5, "size": 3, "children": [{"size": 3.5, "name": "2.2", "name-long": "Malnutrition"}, {"size": 4.5, "name": "2.4", "name-long": "Food production/agriculture"}, {"size": 3.5, "name": "6.5", "name-long": "Water resources management"}, {"size": 4.0, "name": "6.6", "name-long": "Water-related ecosystems"}, {"size": 4.0, "name": "12.1", "name-long": "Sustainable consumption/production"}, {"size": 3.0, "name": "12.5", "name-long": "Waste"}, {"size": 3.0, "name": "13.1", "name-long": "Climate change adaptation"}, {"size": 3.0, "name": "14.1", "name-long": "Marine pollution"}, {"size": 3.0, "name": "15.2", "name-long": "Forests"}], "name": "14.4", "name-long": "Fishery"}, {"total": 14.5, "size": 1, "children": [{"size": 1.0, "name": "2.2", "name-long": "Malnutrition"}, {"size": 2.0, "name": "2.4", "name-long": "Food production/agriculture"}, {"size": 2.0, "name": "6.5", "name-long": "Water resources management"}, {"size": 2.5, "name": "6.6", "name-long": "Water-related ecosystems"}, {"size": 2.0, "name": "12.1", "name-long": "Sustainable consumption/production"}, {"size": 2.0, "name": "12.5", "name-long": "Waste"}, {"size": 1.0, "name": "13.1", "name-long": "Climate change adaptation"}, {"size": 1.0, "name": "14.4", "name-long": "Fishery"}, {"size": 1.0, "name": "15.2", "name-long": "Forests"}], "name": "14.1", "name-long": "Marine pollution"}, {"total": 31.5, "size": 3, "children": [{"size": 3.0, "name": "2.2", "name-long": "Malnutrition"}, {"size": 4.0, "name": "2.4", "name-long": "Food production/agriculture"}, {"size": 3.5, "name": "6.5", "name-long": "Water resources management"}, {"size": 4.5, "name": "6.6", "name-long": "Water-related ecosystems"}, {"size": 3.0, "name": "12.1", "name-long": "Sustainable consumption/production"}, {"size": 3.0, "name": "12.5", "name-long": "Waste"}, {"size": 4.0, "name": "13.1", "name-long": "Climate change adaptation"}, {"size": 3.0, "name": "14.4", "name-long": "Fishery"}, {"size": 3.5, "name": "14.1", "name-long": "Marine pollution"}], "name": "15.2", "name-long": "Forests"}], "name": "15.5", "name-long": "Biodiversity"}